drf_mocker/__init__.py
drf_mocker/mixins.py
drf_mocker/views.py
drf_mocker/viewsets.py
drf_mocker-0.1.0.dist-info/METADATA
drf_mocker-0.1.0.dist-info/WHEEL
drf_mocker-0.1.0.dist-info/licenses/LICENSE
drf_mocker-0.1.0.dist-info/RECORD
