Metadata-Version: 2.4
Name: drf-mocker
Version: 0.1.0
Summary: A Django DRF mock response tool
Project-URL: Homepage, https://github.com/khodealib/drf-mock-response
Author-email: Ali Bagheri <khodealib@gmail.com>
License: MIT License
License-File: LICENSE
Keywords: django,drf,mock,response
Classifier: Framework :: Django
Classifier: Framework :: Django :: 3.2
Classifier: Framework :: Django :: 4.2
Classifier: Framework :: Django :: 5.2
Classifier: License :: OSI Approved :: MIT License
Classifier: Operating System :: OS Independent
Classifier: Programming Language :: Python :: 3
Requires-Python: >=3.10
Requires-Dist: django>=3.2
Requires-Dist: djangorestframework>=3.12
